maskword/__init__.py
maskword/maskfactory.py
maskword-0.0.0.1.dist-info/LICENSE
maskword-0.0.0.1.dist-info/METADATA
maskword-0.0.0.1.dist-info/WHEEL
maskword-0.0.0.1.dist-info/top_level.txt
maskword-0.0.0.1.dist-info/RECORD
