Metadata-Version: 2.1
Name: maskword
Version: 0.0.0.1
Summary: masking word package
Home-page: https://github.com/hyeonsangjeon/maskword.git
Author: hyeonsangjeon
Author-email: wingnut0310@gmail.com
Classifier: Programming Language :: Python :: 3.8
Classifier: License :: OSI Approved :: MIT License
Classifier: Operating System :: OS Independent
License-File: LICENSE
Requires-Dist: nlptutti
